multiboot/__init__.py
multiboot/cli.py
multiboot-0.9.1.dist-info/METADATA
multiboot-0.9.1.dist-info/WHEEL
multiboot-0.9.1.dist-info/entry_points.txt
multiboot-0.9.1.dist-info/licenses/LICENSE
multiboot-0.9.1.dist-info/RECORD
