Metadata-Version: 2.4
Name: multiboot
Version: 0.9.1
Summary: Upload GBA multiboot payloads via Raspberry Pi Pico
Project-URL: Documentation, https://github.com/loopj/gba-multiboot-pico#readme
Project-URL: Issues, https://github.com/loopj/gba-multiboot-pico/issues
Project-URL: Source, https://github.com/loopj/gba-multiboot-pico
Author-email: James Smith <james@loopj.com>
License: MIT
License-File: LICENSE
Requires-Python: >=3.10
Requires-Dist: pyserial
Requires-Dist: rich
Provides-Extra: dev
Requires-Dist: ruff==0.11.8; extra == 'dev'
